DIYables_MicroPython_Ultrasonic_Sensor/DIYables_MicroPython_Ultrasonic_Sensor.py
DIYables_MicroPython_Ultrasonic_Sensor/__init__.py
DIYables_MicroPython_Ultrasonic_Sensor-0.1.1.dist-info/LICENSE
DIYables_MicroPython_Ultrasonic_Sensor-0.1.1.dist-info/METADATA
DIYables_MicroPython_Ultrasonic_Sensor-0.1.1.dist-info/WHEEL
DIYables_MicroPython_Ultrasonic_Sensor-0.1.1.dist-info/top_level.txt
DIYables_MicroPython_Ultrasonic_Sensor-0.1.1.dist-info/RECORD
