Metadata-Version: 2.1
Name: DIYables_MicroPython_Ultrasonic_Sensor
Version: 0.1.1
Summary: MicroPython Library for Ultrasonic Sensor, created by DIYables
Home-page: https://diyables.io
Author: DIYables
Author-email: DIYables.io@gmail.com
Classifier: Programming Language :: Python :: Implementation :: MicroPython
Classifier: License :: OSI Approved :: MIT License
Classifier: Operating System :: OS Independent
Requires-Python: >=3.6
License-File: LICENSE
